earthml/__init__.py
earthml/geodata_to_geohash.py
earthml-0.4.dist-info/LICENSE
earthml-0.4.dist-info/METADATA
earthml-0.4.dist-info/WHEEL
earthml-0.4.dist-info/top_level.txt
earthml-0.4.dist-info/RECORD
